[
    {
        "icon": "mdi-tag-multiple",
        "title": "Cadastros",
        "items": [
            {
                "icon": "mdi-tag-plus",
                "title": "Produto compra",
                "name": "register-product",
                "backUrl": "/product",
                "auth": false,
                "child": false
            },
            {
                "icon": "",
                "title": "",
                "name": "register-product-id",
                "backUrl": "/product-id",
                "auth": false,
                "child": true
            },
            {
                "icon": "",
                "title": "",
                "name": "register-product-id-cost-table",
                "backUrl": "/product-cost-table",
                "auth": false,
                "child": true
            },
            {
                "icon": "",
                "title": "",
                "name": "register-product-id-status-table",
                "backUrl": "/product-status-table",
                "auth": false,
                "child": true
            },
            {
                "icon": "",
                "title": "",
                "name": "register-product-id-storage-location",
                "backUrl": "/product-storage-location",
                "auth": false,
                "child": true
            },
            {
                "icon": "",
                "title": "",
                "name": "register-product-id-type-type_id",
                "backUrl": "/product-type",
                "auth": false,
                "child": true
            },
            {
                "icon": "",
                "title": "",
                "name": "register-product-id-imagens",
                "backUrl": "/product-imagens",
                "auth": false,
                "child": true
            },
            {
                "icon": "mdi-tag-minus",
                "title": "Produto venda",
                "name": "register-product-sell",
                "backUrl": "/product-sell",
                "auth": false,
                "child": false
            },
            {
                "icon": "",
                "title": "",
                "name": "register-product-sell-id",
                "backUrl": "/product-sell-id",
                "auth": false,
                "child": true
            },
            {
                "icon": "",
                "title": "",
                "name": "register-product-sell-id-logs",
                "backUrl": "/product-sell-id-logs",
                "auth": false,
                "child": true
            },
            {
                "icon": "mdi-image-area",
                "title": "Validação de imagens",
                "name": "register-validate-image",
                "backUrl": "/validate-products-image",
                "auth": false,
                "child": false
            },
            {
                "icon": "mdi-truck-fast",
                "title": "Fornecedores",
                "name": "register-supplier",
                "backUrl": "/supplier",
                "auth": false,
                "child": false
            },
            {
                "icon": "mdi-devices",
                "title": "Aparelhos",
                "name": "register-device",
                "backUrl": "/apparatus",
                "auth": false,
                "child": false
            },
            {
                "icon": "",
                "title": "",
                "name": "register-device-classification-apparatus",
                "backUrl": "/classification-apparatus",
                "auth": false,
                "child": true
            },
            {
                "icon": "mdi-account-group",
                "title": "Clientes",
                "name": "register-client",
                "backUrl": "/client",
                "auth": false,
                "child": false
            },
            {
                "icon": "",
                "title": "",
                "name": "register-client-id",
                "backUrl": "/clients-id",
                "auth": false,
                "child": true
            },
            {
                "icon": "",
                "title": "",
                "name": "register-client-new",
                "backUrl": "/clients-new",
                "auth": false,
                "child": true
            },
            {
                "icon": "mdi-warehouse",
                "title": "Almoxarifados",
                "name": "register-warehouse",
                "backUrl": "/erp-warehouses",
                "auth": false,
                "child": false
            },
            {
                "icon": "mdi-archive",
                "title": "Embalagens",
                "name": "register-package",
                "backUrl": "/package",
                "auth": false,
                "child": false
            }
        ]
    },
    {
        "icon": "mdi-clipboard-text",
        "title": "Compras",
        "items": [
            {
                "icon": "mdi-view-carousel",
                "title": "Pedidos de compra",
                "name": "purchase-order",
                "backUrl": "/purchase-control",
                "auth": false,
                "child": false
            },
            {
                "icon": "",
                "title": "",
                "name": "purchase-order-id",
                "backUrl": "/purchase-control-id",
                "auth": false,
                "child": true
            },
            {
                "icon": "",
                "title": "",
                "name": "purchase-order-new",
                "backUrl": "/purchase-control-new",
                "auth": false,
                "child": true
            },
            {
                "icon": "",
                "title": "",
                "name": "purchase-order-validation-send-limite",
                "backUrl": "/purchase-control-validation-send-limite",
                "auth": false,
                "child": true
            },
            {
                "icon": "mdi-form-select",
                "title": "Solicitações de compra",
                "name": "purchase-request",
                "backUrl": "/purchase-request",
                "auth": false,
                "child": false
            },
            {
                "icon": "",
                "title": "",
                "name": "purchase-request-id",
                "backUrl": "/purchase-request-id",
                "auth": false,
                "child": true
            },
            {
                "icon": "",
                "title": "",
                "name": "purchase-request-new",
                "backUrl": "/purchase-request-new",
                "auth": false,
                "child": true
            },
            {
                "icon": "",
                "title": "",
                "name": "purchase-request-export",
                "backUrl": "/purchase-request-export",
                "auth": false,
                "child": true
            },
            {
                "icon": "mdi-currency-usd",
                "title": "Cotações",
                "name": "purchase-quotation",
                "backUrl": "/quotation",
                "auth": false,
                "child": false
            },
            {
                "icon": "mdi-store",
                "title": "Pedidos mercado livre",
                "name": "purchase-order-ml",
                "backUrl": "/orders-finality-stock-ml",
                "auth": false,
                "child": false
            },
            {
                "icon": "mdi-invoice-import",
                "title": "Pedidos importação",
                "name": "purchase-order-import",
                "backUrl": "/import-orders",
                "auth": false,
                "child": false
            },
            {
                "icon": "mdi-paperclip",
                "title": "Insumos",
                "name": "purchase-insumos",
                "backUrl": "/input-materials",
                "auth": false,
                "child": false
            },
            {
                "icon": "mdi-package-check",
                "title": "Salvados",
                "name": "purchase-saved-rma",
                "backUrl": "/saved-rma",
                "auth": false,
                "child": false
            },
            {
                "icon": "",
                "title": "",
                "name": "register-saved-rma-id",
                "backUrl": "/saved-rma-id",
                "auth": false,
                "child": true
            },
            {
                "icon": "",
                "title": "",
                "name": "register-saved-rma-id-apparatus",
                "backUrl": "/saved-apparatus-rma",
                "auth": false,
                "child": true
            },
            {
                "icon": "",
                "title": "",
                "name": "register-saved-rma-id-apparatus-apparatus",
                "backUrl": "/saved-apparatus-rma-id",
                "auth": false,
                "child": true
            },
            {
                "icon": "",
                "title": "",
                "name": "register-saved-rma-id-apparatus-apparatus-image",
                "backUrl": "/saved-apparatus-rma-id-image",
                "auth": false,
                "child": true
            },
            {
                "icon": "",
                "title": "",
                "name": "register-saved-rma-id-products",
                "backUrl": "/saved-products-rma",
                "auth": false,
                "child": true
            },
            {
                "icon": "mdi-receipt-text-clock",
                "title": "Pendencias de preço",
                "name": "purchase-pending-price",
                "backUrl": "/pending-price",
                "auth": false,
                "child": false
            },
            {
                "icon": "mdi-cash-check",
                "title": "Validação de preço mercado livre",
                "name": "purchase-validate-price-ml",
                "backUrl": "/validate-price-percentage",
                "auth": false,
                "child": false
            },
            {
                "icon": "mdi-lan-check",
                "title": "Validação de estoque virtual",
                "name": "purchase-validate-stock-virtual",
                "backUrl": "/validate-virtual-stock",
                "auth": false,
                "child": false
            }
        ]
    },
    {
        "icon": "mdi-cart",
        "title": "Vendas",
        "items": [
            {
                "icon": "mdi-cart-percent",
                "title": "Pedidos de separação",
                "name": "sale-separation-requests",
                "backUrl": "/sales-orders-separation",
                "auth": false,
                "child": false
            },
            {
                "icon": "",
                "title": "",
                "name": "sale-verification-order-erp-status",
                "backUrl": "/sales-orders-separation-erp",
                "auth": false,
                "child": true
            },
            {
                "icon": "mdi-truck-check-outline",
                "title": "Validação de envio",
                "name": "sale-shipping-validation",
                "backUrl": "/shipping-validation",
                "auth": false,
                "child": false
            }, 
            {
                "icon": "mdi-content-save-all",
                "title": "Garantia",
                "name": "sale-warranty",
                "backUrl": "/garantia-rma",
                "auth": false,
                "child": false
            },
            {
                "icon": "",
                "title": "",
                "name": "sale-warranty-id",
                "backUrl": "/garantia-rma-id",
                "auth": false,
                "child": true
            },
            {
                "icon": "",
                "title": "",
                "name": "sale-warranty-new",
                "backUrl": "/garantia-rma-new",
                "auth": false,
                "child": true
            },
            {
                "icon": "mdi-chart-arc",
                "title": "Indicadores",
                "name": "sale-indicators",
                "backUrl": "/indicators-orders",
                "auth": false,
                "child": false
            },
            {
                "icon": "mdi-cart-percent",
                "title": "Aparelhos à venda",
                "name": "sale-sell-device",
                "backUrl": "/sell-device",
                "auth": false,
                "child": false
            }
            
        ]
    },
    {
        "icon": "mdi-toolbox-outline",
        "title": "Serviços",
        "items": [
            {
                "icon": "mdi-webpack",
                "title": "Ordem de serviço",
                "name": "service-order",
                "backUrl": "/service-order",
                "auth": false,
                "child": false
            },
            {
                "icon": "",
                "title": "",
                "name": "service-order-id",
                "backUrl": "/service-order-id",
                "auth": false,
                "child": true
            },
            {
                "icon": "",
                "title": "",
                "name": "service-order-new",
                "backUrl": "/service-order-new",
                "auth": false,
                "child": true
            },
            {
                "icon": "",
                "title": "",
                "name": "service-order-id-technical-analysis",
                "backUrl": "/technical-observation",
                "auth": false,
                "child": true
            },
            {
                "icon": "",
                "title": "",
                "name": "service-order-id-budget",
                "backUrl": "/service-order-budget",
                "auth": false,
                "child": true
            },
            {
                "icon": "",
                "title": "",
                "name": "service-order-id-payment",
                "backUrl": "/service-order-payments",
                "auth": false,
                "child": true
            },
            {
                "icon": "",
                "title": "",
                "name": "service-order-id-central-information",
                "backUrl": "/client-observation",
                "auth": false,
                "child": true
            },
            {
                "icon": "",
                "title": "",
                "name": "service-order-id-crm",
                "backUrl": "/internal-observation",
                "auth": false,
                "child": true
            },
            {
                "icon": "",
                "title": "",
                "name": "service-order-id-files",
                "backUrl": "/service-order-id-files",
                "auth": false,
                "child": true
            },
            {
                "icon": "",
                "title": "",
                "name": "service-order-id-history",
                "backUrl": "/service-order-id-history",
                "auth": false,
                "child": true
            },
            {
                "icon": "",
                "title": "",
                "name": "service-order-id-logs",
                "backUrl": "/service-order-status-log",
                "auth": false,
                "child": true
            },
            {
                "icon": "mdi-cash-register",
                "title": "Controle de caixa",
                "name": "service-cash-control",
                "backUrl": "/reception-cash-control",
                "auth": false,
                "child": false
            },
            {
                "icon": "mdi-card-account-details",
                "title": "Crm",
                "name": "service-crm",
                "backUrl": "/crm",
                "auth": false,
                "child": false
            },
            {
                "icon": "mdi-account-wrench",
                "title": "Atendimento externo",
                "name": "service-external",
                "backUrl": "/service-order/general-report",
                "auth": false,
                "child": false
            }
        ]
    },
    {
        "icon": "mdi-cube-send",
        "title": "Estoque",
        "items": [
            {
                "icon": "mdi-tag-multiple",
                "title": "Etiqueta de produto",
                "name": "stock-product-label",
                "backUrl": "/stock-tag-control",
                "auth": false,
                "child": false
            },
            {
                "icon": "",
                "title": "",
                "name": "stock-product-label-manual_separation",
                "backUrl": "/manual_separation",
                "auth": false,
                "child": true
            },
            {
                "icon": "mdi-package-variant",
                "title": "Local de armazenagem",
                "name": "stock-storage-location",
                "backUrl": "/storage-location",
                "auth": false,
                "child": false
            },
            {
                "icon": "mdi-help-box",
                "title": "Sugestão local de armazenagem",
                "name": "stock-suggested-storage-location",
                "backUrl": "/suggested-storage-location",
                "auth": false,
                "child": false
            },
            {
                "icon": "mdi-file-arrow-up-down-outline",
                "title": "Controle de empréstimo",
                "name": "stock-product-loan",
                "backUrl": "/product-loan",
                "auth": false,
                "child": false
            },
            {
                "icon": "mdi-receipt-text-check",
                "title": "Recebimento",
                "name": "stock-receipt",
                "backUrl": "/receivement",
                "auth": false,
                "child": false
            },
            {
                "icon": "mdi-math-log",
                "title": "Separação",
                "name": "stock-separation-log",
                "backUrl": "/order-picking",
                "auth": false,
                "child": false
            },
            {
                "icon": "mdi-archive-settings",
                "title": "Gestão de coletas",
                "name": "stock-parts-collection-management",
                "backUrl": "/parts-collection-management",
                "auth": false,
                "child": false
            },
            {
                "icon": "",
                "title": "",
                "name": "stock-parts-collection-management-id",
                "backUrl": "/parts-collection-management-id",
                "auth": false,
                "child": true
            },
            {
                "icon": "",
                "title": "",
                "name": "stock-parts-collection-management-id-logs",
                "backUrl": "/parts-collection-management-id-logs",
                "auth": false,
                "child": true
            },
            {
                "icon": "",
                "title": "",
                "name": "stock-parts-collection-management-new",
                "backUrl": "/parts-collection-management-new",
                "auth": false,
                "child": true
            },
            {
                "icon": "mdi-poll",
                "title": "Estoque fiscal",
                "name": "stock-tax-stock",
                "backUrl": "/tax-stock",
                "auth": false,
                "child": false
            }
        ]
    },
    {
        "icon": "mdi-transfer",
        "title": "Expedição",
        "items": [
            {
                "icon": "mdi-receipt-text-check-outline",
                "title": "Checkout",
                "name": "expedition-check-out",
                "backUrl": "/Checkout",
                "auth": false,
                "child": false
            },
            {
                "icon": "mdi-timeline-check-outline",
                "title": "Gerencial checkout",
                "name": "expedition-manager-check-out",
                "backUrl": "/manage-checkout",
                "auth": false,
                "child": false
            },
            {
                "icon": "",
                "title": "",
                "name": "expedition-check-out-history",
                "backUrl": "/Checkout-history",
                "auth": false,
                "child": true
            },
            {
                "icon": "mdi-notebook-outline",
                "title": "Romaneio",
                "name": "expedition-romaneio",
                "backUrl": "/romaneio",
                "auth": false,
                "child": false
            },
            {
                "icon": "",
                "title": "",
                "name": "expedition-romaneio-new",
                "backUrl": "/romaneio-new",
                "auth": false,
                "child": true
            },
            {
                "icon": "mdi-clock-time-eight",
                "title": "Horario de corte",
                "name": "expedition-cut-time",
                "backUrl": "/carrier-cut-time",
                "auth": false,
                "child": false
            },
            {
                "icon": "mdi-priority-high",
                "title": "Urgência de Envio",
                "name": "expedition-shipping-urgency",
                "backUrl": "/shipping-urgency",
                "auth": false,
                "child": false
            }
        ]
    },
    {
        "icon": "mdi-server-security",
        "title": "Integrações",
        "items": [
            {
                "icon": "mdi-server-network",
                "title": "Erros sincronização",
                "name": "integration-sync-errors",
                "backUrl": "/product-sync-errors",
                "auth": false,
                "child": false
            },
            {
                "icon": "mdi-lan-pending",
                "title": "Erros de integração",
                "name": "integration-Integration-errors",
                "backUrl": "/pendency",
                "auth": false,
                "child": false
            },
            {
                "icon": "mdi-alpha-e-circle",
                "title": "E-commerces",
                "name": "integration-ecommerce",
                "backUrl": "/ecommerce",
                "auth": false,
                "child": false
            },
            {
                "icon": "mdi-cloud-braces",
                "title": "Log de Integrações",
                "name": "integration-log",
                "backUrl": "/integration",
                "auth": false,
                "child": false
            },
            {
                "icon": "mdi-bug",
                "title": "Diff report",
                "name": "integration-diff-report",
                "backUrl": "/diff-report",
                "auth": false,
                "child": false
            }
        ]
    },
    {
        "icon": "mdi-server-security",
        "title": "Automação",
        "items": [
            {
                "icon": "mdi-robot",
                "title": "Puppeteer",
                "name": "automation-puppeteer",
                "backUrl": "/automation/puppeteer",
                "auth": false,
                "child": false
            }
        ]
    },
    {
        "icon": "mdi-cog",
        "title": "Options",
        "items": [
            {
                "icon": null,
                "title": "Favoritos",
                "name": "option-index-favorite",
                "backUrl": "/favorite-routes",
                "auth": false,
                "child": false
            },
            {
                "icon": null,
                "title": "Relatorios",
                "name": "option-index-reports",
                "backUrl": "/reports",
                "auth": false,
                "child": false
            },
            {
                "icon": null,
                "title": "Senhas de fornecedores",
                "name": "option-index-supplier-passwords",
                "backUrl": "/supplier-passwords",
                "auth": false,
                "child": false
            },
            {
                "icon": null,
                "title": "",
                "name": "option-index-supplier-passwords-log",
                "backUrl": "/supplier-passwords-logs",
                "auth": false,
                "child": true
            },
            {
                "icon": null,
                "title": "",
                "name": "option-index-supplier-passwords-id",
                "backUrl": "/supplier-passwords-id",
                "auth": false,
                "child": true
            },
            {
                "icon": null,
                "title": "Cidade",
                "name": "option-index-city",
                "backUrl": "/city",
                "auth": false,
                "child": false
            },
            {
                "icon": null,
                "title": "Região",
                "name": "option-index-region",
                "backUrl": "/region",
                "auth": false,
                "child": false
            },
            {
                "icon": null,
                "title": "Data limite",
                "name": "option-index-limit-date",
                "backUrl": "/limit-date-purchase-control",
                "auth": false,
                "child": false
            },
            {
                "icon": null,
                "title": "Template produtos",
                "name": "option-index-product-template",
                "backUrl": "/product-settings",
                "auth": false,
                "child": false
            },
            {
                "icon": null,
                "title": "Tabela de preço balcão",
                "name": "option-index-table-price-desk",
                "backUrl": "/table-price",
                "auth": false,
                "child": false
            },
            {
                "icon": null,
                "title": "Impressoras",
                "name": "option-index-printer",
                "backUrl": "/printers-settings",
                "auth": false,
                "child": false
            },
            {
                "icon": null,
                "title": "Envios",
                "name": "option-index-shipment",
                "backUrl": "/shipment-orders",
                "auth": false,
                "child": false
            },
            {
                "icon": null,
                "title": "Filtros/Grids",
                "name": "option-index-grid-filter",
                "backUrl": "/custom-filters",
                "auth": false,
                "child": false
            },
            {
                "icon": null,
                "title": "",
                "name": "option-index-grid-filter-config-initial",
                "backUrl": "/custom-filters-config-initial",
                "auth": false,
                "child": true
            },
            {
                "icon": null,
                "title": "Configurações iniciais",
                "name": "option-index-grid-filter-config-initial",
                "backUrl": "/custom-filters/config-initial",
                "auth": false,
                "child": true
            },
            {
                "icon": null,
                "title": "Sistema",
                "name": "option-index-system",
                "backUrl": "/manage-system",
                "auth": false,
                "child": false
            },
            {
                "icon": null,
                "title": "Empresas",
                "name": "option-index-company",
                "backUrl": "/companies",
                "auth": false,
                "child": false
            },
            {
                "icon": null,
                "title": "Faturamento",
                "name": "option-index-invoicing",
                "backUrl": "/invoice-rule",
                "auth": false,
                "child": false
            },
            {
                "icon": null,
                "title": "Configurações de notificações",
                "name": "option-index-notifications-config",
                "backUrl": "/notifications-config",
                "auth": false,
                "child": false
            },
            {
                "icon": null,
                "title": "Permissões",
                "name": "option-index-permission",
                "backUrl": "/group",
                "auth": false,
                "child": false
            },
            {
                "icon": null,
                "title": "",
                "name": "option-index-permission-id",
                "backUrl": "/group-id",
                "auth": false,
                "child": true
            },
            {
                "icon": null,
                "title": "Usuarios",
                "name": "option-index-user",
                "backUrl": "/user",
                "auth": false,
                "child": false
            },
            {
                "icon": null,
                "title": "Lista de acesso",
                "name": "option-index-access",
                "backUrl": "/access-list",
                "auth": false,
                "child": false
            },
            {
                "icon": null,
                "title": "Log de acesso",
                "name": "option-index-log-access",
                "backUrl": "/login-log",
                "auth": false,
                "child": false
            }
        ]
    }
]